an_toolkit/__init__.py
an_toolkit/toolkit.py
an_toolkit-0.4.5.dist-info/licenses/LICENSE
an_toolkit-0.4.5.dist-info/METADATA
an_toolkit-0.4.5.dist-info/WHEEL
an_toolkit-0.4.5.dist-info/top_level.txt
an_toolkit-0.4.5.dist-info/RECORD
