Metadata-Version: 2.4
Name: an_toolkit
Version: 0.4.5
Summary: A package for an_toolkit.
Home-page: https://github.com/Atsushi888/Atsushi888
Author: Atsushi888
Author-email: Atsushi888 <vtgrotxu@gmail.com>
Project-URL: Homepage, https://github.com/Atsushi888/an_toolkit
Project-URL: Repository, https://github.com/Atsushi888/an_toolkit
Requires-Python: >=3.6
License-File: LICENSE
Dynamic: author
Dynamic: home-page
Dynamic: license-file
Dynamic: requires-python
